youtube_up/__init__.py
youtube_up/__main__.py
youtube_up/metadata.py
youtube_up/py.typed
youtube_up/schema.py
youtube_up/uploader.py
youtube_up-0.5.6.dist-info/METADATA
youtube_up-0.5.6.dist-info/WHEEL
youtube_up-0.5.6.dist-info/entry_points.txt
youtube_up-0.5.6.dist-info/RECORD
