Metadata-Version: 2.3
Name: youtube-up
Version: 0.5.6
Summary: Upload videos to YouTube using the internal YouTube API. Does not require an API key.
Home-page: https://github.com/7x11x13/youtube-up
Keywords: YouTube,upload
Author: 7x11x13
Author-email: x7x11x13@gmail.com
Requires-Python: >=3.10,<4.0
Classifier: Programming Language :: Python :: 3
Classifier: Programming Language :: Python :: 3.10
Classifier: Programming Language :: Python :: 3.11
Classifier: Programming Language :: Python :: 3.12
Classifier: Programming Language :: Python :: 3.13
Requires-Dist: dataclasses-json (>=0.6.2,<0.7.0)
Requires-Dist: requests (>=2.32.3,<3.0.0)
Requires-Dist: selenium (>=4.11.2,<5.0.0)
Requires-Dist: selenium-wire-2 (>=0.2.1,<0.3.0)
Requires-Dist: tqdm (>=4.66.1,<5.0.0)
Project-URL: Documentation, https://7x11x13.xyz/youtube-up/youtube_up
Project-URL: Repository, https://github.com/7x11x13/youtube-up
